nexgml/__init__.py
nexgml/amo/__init__.py
nexgml/amo/forlinear/__init__.py
nexgml/amo/forlinear/derivs.py
nexgml/amo/forlinear/losses.py
nexgml/amo/forlinear/penalties.py
nexgml/amo/forlinear/probas.py
nexgml/amo/fortree/__init__.py
nexgml/amo/fortree/impurities.py
nexgml/gradient_supported/__init__.py
nexgml/gradient_supported/basic_models/GSBasicClassifier.py
nexgml/gradient_supported/basic_models/GSBasicRegressor.py
nexgml/gradient_supported/basic_models/__init__.py
nexgml/gradient_supported/intense_models/GSIntenseClassifier.py
nexgml/gradient_supported/intense_models/GSIntenseRegressor.py
nexgml/gradient_supported/intense_models/__init__.py
nexgml/gradient_supported/penalty_based/ElasticNetClassifier.py
nexgml/gradient_supported/penalty_based/ElasticNetRegressor.py
nexgml/gradient_supported/penalty_based/L1Classifier.py
nexgml/gradient_supported/penalty_based/L1Regressor.py
nexgml/gradient_supported/penalty_based/L2Classifier.py
nexgml/gradient_supported/penalty_based/L2Regressor.py
nexgml/gradient_supported/penalty_based/__init__.py
nexgml/gradient_supported/regression_based/MRClassifier.py
nexgml/gradient_supported/regression_based/SRClassifier.py
nexgml/gradient_supported/regression_based/__init__.py
nexgml/guardians/__init__.py
nexgml/guardians/arr.py
nexgml/guardians/detect.py
nexgml/indexing/__init__.py
nexgml/indexing/detecting.py
nexgml/indexing/encoding.py
nexgml/indexing/indexing.py
nexgml/metrics/__init__.py
nexgml/metrics/forclassi.py
nexgml/metrics/forregress.py
nexgml/tree_models/__init__.py
nexgml/tree_models/forest_backend/FBClassifier.py
nexgml/tree_models/forest_backend/FBRegressor.py
nexgml/tree_models/forest_backend/__init__.py
nexgml/tree_models/tree_backend/TBClassifier.py
nexgml/tree_models/tree_backend/TBRegressor.py
nexgml/tree_models/tree_backend/__init__.py
nexgml-1.5.1.dist-info/licenses/LICENSE
nexgml-1.5.1.dist-info/METADATA
nexgml-1.5.1.dist-info/WHEEL
nexgml-1.5.1.dist-info/top_level.txt
nexgml-1.5.1.dist-info/RECORD
