Metadata-Version: 2.4
Name: nexgml
Version: 1.5.1
Summary: NexGML — Next Generation Machine Learning (educational ML utilities)
Author: Nexo-kun
Author-email: nexokun.contact@gmail.com
License: MIT
Project-URL: Homepage, https://github.com/Next-Aura/Nexarians
Project-URL: Documentation, https://github.com/Next-Aura/Nexarians#documentation
Project-URL: Source, https://github.com/Next-Aura/Nexarians
Project-URL: Tracker, https://github.com/Next-Aura/Nexarians/issues
Requires-Python: >=3.10
License-File: LICENSE
Requires-Dist: numpy>=1.23
Requires-Dist: scipy>=1.10
Requires-Dist: typing_extensions
Dynamic: author-email
Dynamic: license-file
Dynamic: requires-python
